trainlogger/__init__.py
trainlogger/basics.py
trainlogger/extract_info.py
trainlogger/trainer.py
trainlogger-0.1.2.dist-info/METADATA
trainlogger-0.1.2.dist-info/WHEEL
trainlogger-0.1.2.dist-info/top_level.txt
trainlogger-0.1.2.dist-info/RECORD
