Metadata-Version: 2.1
Name: trainlogger
Version: 0.1.2
Summary: A Python package
Home-page: https://github.com/jonas-sth/trainlogger
Author: Jonas Steinhäuser
Author-email: 
Classifier: Development Status :: 1 - Planning
Classifier: Intended Audience :: Science/Research
Classifier: Programming Language :: Python :: 3.8
Requires-Dist: numpy
Requires-Dist: torch
Requires-Dist: torchmetrics
Requires-Dist: tqdm
Requires-Dist: pandas
Requires-Dist: tensorflow
